<problem display_name="Question of the assignment 3.2.3" markdown="&gt;&gt;In September 2016, which facility had the highest HIV test positivity rate?&lt;&lt;&#10;[[Catfish Private Hospital, Lightfish Primary Health Care Centre, (Poodle Private Medical Practice), Pug Private Medical Practice]]&#10;&#10;[explanation]&#10;Poodle Private Medical Practice had the highest HIV test positivity rate&#10;[explanation]" max_attempts="3" rerandomize="always" show_reset_button="true" showanswer="finished" submission_wait_seconds="30">
<p>In September 2016, which facility had the highest HIV test positivity rate?</p>

<optionresponse>
  <optioninput label="In September 2016, which facility had the highest HIV test positivity rate?" options="('Catfish Private Hospital','Lightfish Primary Health Care Centre','Poodle Private Medical Practice','Pug Private Medical Practice')" correct="Poodle Private Medical Practice"/>
</optionresponse>

<solution>
<div class="detailed-solution">
<p>Explanation</p>

<p>Poodle Private Medical Practice had the highest HIV test positivity rate</p>

</div>
</solution>
</problem>
